facesdk
